cleanbib/__init__.py
cleanbib/bib_cleaner.py
cleanbib/similar_authors.py
cleanbib/warning_handler.py
cleanbib-0.1.1.dist-info/METADATA
cleanbib-0.1.1.dist-info/WHEEL
cleanbib-0.1.1.dist-info/licenses/LICENSE
cleanbib-0.1.1.dist-info/RECORD
