Metadata-Version: 2.4
Name: cleanbib
Version: 0.1.1
Summary: A tool for parsing and cleaning BibTex and BibLaTex files for better LaTex bibliography formatting.
Project-URL: Documentation, https://github.com/harryziyuhe/cleanbib#readme
Project-URL: Issues, https://github.com/harryziyuhe/cleanbib/issues
Project-URL: Source, https://github.com/harryziyuhe/cleanbib
Author-email: Harry He <zih028@ucsd.edu>
License-Expression: MIT
License-File: LICENSE
Keywords: BibLaTex,BibTex,LaTex
Requires-Python: >=3.8
Requires-Dist: requests
Requires-Dist: tqdm
